datadog/__init__.py
datadog/apps.py
datadog/instrument.py
datadog/middleware.py
dbtp_django_datadog-0.1.0.dist-info/METADATA
dbtp_django_datadog-0.1.0.dist-info/WHEEL
dbtp_django_datadog-0.1.0.dist-info/RECORD
