Metadata-Version: 2.3
Name: dbtp-django-datadog
Version: 0.1.0
Summary: A package to configuring datadog for DBT applications running in DBT Platform (AWS copilot/fargate)
Author: sre@digital.trade.gov.uk
Requires-Python: >=3.11
Classifier: Programming Language :: Python :: 3
Classifier: Programming Language :: Python :: 3.11
Classifier: Programming Language :: Python :: 3.12
Classifier: Programming Language :: Python :: 3.13
Requires-Dist: ddtrace (>=3.12.0,<4.0.0)
Requires-Dist: django (>=5.2.5,<6.0.0)
